tf2kerassurgeon/__init__.py
tf2kerassurgeon/identify.py
tf2kerassurgeon/operations.py
tf2kerassurgeon/surgeon.py
tf2kerassurgeon/utils.py
tf2_keras_surgeon-0.0.1.dist-info/LICENSE
tf2_keras_surgeon-0.0.1.dist-info/METADATA
tf2_keras_surgeon-0.0.1.dist-info/WHEEL
tf2_keras_surgeon-0.0.1.dist-info/top_level.txt
tf2_keras_surgeon-0.0.1.dist-info/RECORD
