Metadata-Version: 2.1
Name: tf2-keras-surgeon
Version: 0.0.1
Summary: A library for performing network surgery on trained tensorflow 2 keras models.
Home-page: https://github.com/cs-jsi/tf2-keras-surgeon
Author: Ben Whetton, Raukk, Jure Vreca
Maintainer: Jure Vreca
Maintainer-email: jure.vreca@ijs.si
License: MIT
Classifier: License :: OSI Approved :: MIT License
Classifier: Programming Language :: Python :: 3
Classifier: Programming Language :: Python :: 3.9
Classifier: Intended Audience :: Science/Research
Classifier: Topic :: Scientific/Engineering :: Artificial Intelligence
Requires-Python: >=3.6
License-File: LICENSE
Requires-Dist: tensorflow
